slidl/__init__.py
slidl/_version.py
slidl/analysis.py
slidl/annotation.py
slidl/processor.py
slidl/slide.py
slidl/models/deep-tissue-detector_densenet_state-dict.pt
slidl/models/tissuedetector.py
slidl/utils/torch/WholeSlideImageDataset.py
slidl/utils/torch/dice_loss.py
slidl-0.1.dev4.dist-info/LICENSE
slidl-0.1.dev4.dist-info/METADATA
slidl-0.1.dev4.dist-info/WHEEL
slidl-0.1.dev4.dist-info/top_level.txt
slidl-0.1.dev4.dist-info/RECORD
