Metadata-Version: 2.1
Name: slidl
Version: 0.1.dev4
Summary: SliDL: a Python library of pre- and post-processing tools for applying deep learning to whole-slide images
Home-page: https://github.com/markowetzlab/slidl
Author: A.G. Berman, William R. Orchard, Marcel Gehrung
Author-email: florian.markowetz@cruk.cam.ac.uk
License: GNU General Public License v3
Project-URL: Bug Tracker, https://github.com/markowetzlab/slidl/issues
Project-URL: Documentation, https://slidl.readthedocs.io
Project-URL: Source Code, https://github.com/markowetzlab/slidl
Keywords: ai,deep learning,pathology
Platform: UNKNOWN
Classifier: Development Status :: 2 - Pre-Alpha
Classifier: Intended Audience :: Developers
Classifier: License :: OSI Approved :: GNU General Public License v3 (GPLv3)
Classifier: Natural Language :: English
Classifier: Programming Language :: Python :: 3
Classifier: Programming Language :: Python :: 3.7
Classifier: Programming Language :: Python :: 3.8
Requires-Python: >=3.7
Requires-Dist: albumentations
Requires-Dist: joblib
Requires-Dist: matplotlib
Requires-Dist: pandas
Requires-Dist: pyvips
Requires-Dist: scikit-image
Requires-Dist: scikit-learn
Requires-Dist: shapely
Requires-Dist: torch (<=2.0,>=1.0)
Requires-Dist: torchvision (>=0.5.0)
Requires-Dist: tqdm
